lib_dzne_blastn/__init__.py
lib_dzne_blastn-0.2.3.dist-info/LICENSE.txt
lib_dzne_blastn-0.2.3.dist-info/METADATA
lib_dzne_blastn-0.2.3.dist-info/WHEEL
lib_dzne_blastn-0.2.3.dist-info/top_level.txt
lib_dzne_blastn-0.2.3.dist-info/RECORD
