Metadata-Version: 2.1
Name: lib_dzne_blastn
Version: 0.2.3
Summary: Library for using blastn.
Author-email: Johannes <johannes-programming@posteo.org>
License: The MIT License (MIT)
Project-URL: Source, https://github.com/johannes-programming/lib_dzne_blastn
Project-URL: Download, https://pypi.org/project/lib-dzne-blastn/#files
Keywords: blastn
Classifier: License :: OSI Approved :: MIT License
Classifier: Programming Language :: Python
Classifier: Programming Language :: Python :: 3
Requires-Python: >=3.11
License-File: LICENSE.txt
